edu_function_tools/__init__.py
edu_function_tools/apps.py
edu_function_tools/caches.py
edu_function_tools/consts.py
edu_function_tools/enums.py
edu_function_tools/errors.py
edu_function_tools/functions.py
edu_function_tools/general.py
edu_function_tools/helpers.py
edu_function_tools/managers.py
edu_function_tools/models.py
edu_function_tools/presenters.py
edu_function_tools/receivers.py
edu_function_tools/results.py
edu_function_tools/runners.py
edu_function_tools/storages.py
edu_function_tools/strategies.py
edu_function_tools/strings.py
edu_function_tools/tests.py
edu_function_tools/validators.py
edu_function_tools-0.3.0.dist-info/licenses/LICENSE
edu_function_tools-0.3.0.dist-info/METADATA
edu_function_tools-0.3.0.dist-info/WHEEL
edu_function_tools-0.3.0.dist-info/top_level.txt
edu_function_tools-0.3.0.dist-info/RECORD
