Metadata-Version: 2.4
Name: edu-function-tools
Version: 0.3.0
Summary: Компоненты для адаптации библиотеки function-tools
Author-email: BARS Group <education_dev@bars.group>
Project-URL: Homepage, https://stash.bars-open.ru/projects/EDUBASE/repos/edu-function-tools/browse
Project-URL: Repository, https://stash.bars-open.ru/scm/edubase/edu-function-tools.git
Classifier: Development Status :: 5 - Production/Stable
Classifier: Programming Language :: Python :: 3
Classifier: Programming Language :: Python :: 3.9
Classifier: Programming Language :: Python :: 3.10
Classifier: Programming Language :: Python :: 3.11
Classifier: Programming Language :: Python :: 3.12
Classifier: Framework :: Django :: 2.2
Classifier: Framework :: Django :: 3.0
Classifier: Framework :: Django :: 3.1
Classifier: Framework :: Django :: 3.2
Classifier: Framework :: Django :: 4.0
Classifier: Framework :: Django :: 4.1
Classifier: Intended Audience :: Developers
Classifier: Environment :: Web Environment
Requires-Python: >=3.9
License-File: LICENSE
Requires-Dist: transliterate<2
Requires-Dist: Django<5.0,>=3.1
Requires-Dist: celery<5.3,>=4.4.7
Requires-Dist: asyncpg==0.23.0
Requires-Dist: educommon<4,>=3.11.0
Requires-Dist: function-tools<1,>=0.9.0
Requires-Dist: m3-db-utils<1,>=0.3.10
Requires-Dist: uploader-client<1,>=0.2.3
Provides-Extra: dev
Requires-Dist: isort==5.12.0; extra == "dev"
Requires-Dist: ruff==0.6.9; extra == "dev"
Requires-Dist: flake8<7,>=4.0.1; extra == "dev"
Requires-Dist: pytest<8,>=3.2.5; extra == "dev"
Requires-Dist: pytest-cov<5; extra == "dev"
Provides-Extra: docs
Requires-Dist: sphinx<7.5,>=7; extra == "docs"
Requires-Dist: sphinx-autodoc-typehints<2.5,>=2; extra == "docs"
Requires-Dist: myst-parser<3.2,>=3; extra == "docs"
Requires-Dist: sphinx_design<0.7,>=0.6; extra == "docs"
Dynamic: license-file
